{
  "version": "1.0.0",
  "lastScanned": 1777174598070,
  "projectRoot": "c:\\Users\\USER\\Desktop\\블로그 작성",
  "techStack": {
    "languages": [
      {
        "name": "Python",
        "version": null,
        "confidence": "high",
        "markers": [
          "pyproject.toml",
          "requirements.txt"
        ]
      }
    ],
    "frameworks": [],
    "packageManager": "pip",
    "runtime": null
  },
  "build": {
    "buildCommand": null,
    "testCommand": "pytest",
    "lintCommand": "ruff check",
    "devCommand": null,
    "scripts": {}
  },
  "conventions": {
    "namingStyle": null,
    "importStyle": null,
    "testPattern": null,
    "fileOrganization": null
  },
  "structure": {
    "isMonorepo": false,
    "workspaces": [],
    "mainDirectories": [
      "assets",
      "docs",
      "scripts",
      "src"
    ],
    "gitBranches": null
  },
  "customNotes": [],
  "directoryMap": {
    "assets": {
      "path": "assets",
      "purpose": "Static assets",
      "fileCount": 0,
      "lastAccessed": 1777174597658,
      "keyFiles": []
    },
    "dev": {
      "path": "dev",
      "purpose": null,
      "fileCount": 0,
      "lastAccessed": 1777174597659,
      "keyFiles": []
    },
    "docs": {
      "path": "docs",
      "purpose": "Documentation",
      "fileCount": 0,
      "lastAccessed": 1777174597660,
      "keyFiles": []
    },
    "output": {
      "path": "output",
      "purpose": null,
      "fileCount": 0,
      "lastAccessed": 1777174597672,
      "keyFiles": []
    },
    "scripts": {
      "path": "scripts",
      "purpose": "Build/utility scripts",
      "fileCount": 0,
      "lastAccessed": 1777174597673,
      "keyFiles": []
    },
    "skills": {
      "path": "skills",
      "purpose": null,
      "fileCount": 0,
      "lastAccessed": 1777174597677,
      "keyFiles": []
    },
    "slash-commands": {
      "path": "slash-commands",
      "purpose": null,
      "fileCount": 0,
      "lastAccessed": 1777174597678,
      "keyFiles": []
    },
    "src": {
      "path": "src",
      "purpose": "Source code",
      "fileCount": 0,
      "lastAccessed": 1777174597682,
      "keyFiles": []
    }
  },
  "hotPaths": [],
  "userDirectives": []
}